simple_cv2_wrapper.py
simple_cv2_wrapper-0.1.0.dist-info/LICENSE
simple_cv2_wrapper-0.1.0.dist-info/METADATA
simple_cv2_wrapper-0.1.0.dist-info/WHEEL
simple_cv2_wrapper-0.1.0.dist-info/top_level.txt
simple_cv2_wrapper-0.1.0.dist-info/RECORD
