Metadata-Version: 2.1
Name: simple-cv2-wrapper
Version: 0.1.0
Summary: A very simple wrapper for cv2 for usual stuff
Author: Noizrom
License: MIT License        
Project-URL: Homepage, https://github.com/Noizrom/Simple-cv2-wrapper
Classifier: Programming Language :: Python :: 3
Classifier: License :: OSI Approved :: MIT License
Classifier: Development Status :: 3 - Alpha
Classifier: Operating System :: Microsoft :: Windows :: Windows 10
Classifier: Programming Language :: Python :: 3.10
Classifier: Topic :: Multimedia :: Video :: Capture
Classifier: Topic :: Scientific/Engineering :: Image Processing
Classifier: Topic :: Utilities
Requires-Python: >=3.10
License-File: LICENSE
